fringes_gui/__init__.py
fringes_gui/gui.py
fringes_gui/logic.py
fringes_gui/main.py
fringes_gui/numba-blue-icon-rgb.svg
fringes_gui/params.py
fringes_gui/readme.txt
fringes_gui/setters.py
fringes_gui/Xi.svg
fringes_gui-1.0.2.dist-info/LICENSE.txt
fringes_gui-1.0.2.dist-info/METADATA
fringes_gui-1.0.2.dist-info/WHEEL
fringes_gui-1.0.2.dist-info/RECORD
