Metadata-Version: 2.1
Name: Fringes-GUI
Version: 1.0.2
Summary: Graphical user interface for the 'fringes' package.
Home-page: https://github.com/comimag/fringes-gui
License: CC-BY-NC-SA-4.0
Keywords: phase shifting,phase unwrapping,fringe analysis,fringe projection,deflectometry,computational imaging
Author: Christian Kludt
Requires-Python: >=3.10,<3.13
Classifier: Intended Audience :: Education
Classifier: Intended Audience :: Science/Research
Classifier: License :: Other/Proprietary License
Classifier: Programming Language :: Python :: 3
Classifier: Programming Language :: Python :: 3.10
Classifier: Programming Language :: Python :: 3.11
Classifier: Programming Language :: Python :: 3.12
Classifier: Topic :: Scientific/Engineering :: Image Processing
Requires-Dist: asdf (>=3.0.1,<4.0.0)
Requires-Dist: fringes (>=1.1,<1.2)
Requires-Dist: h5py (>=3.9.0,<4.0.0)
Requires-Dist: numpy (>=1.26.1,<2.0.0)
Requires-Dist: opencv-contrib-python (>=4.7.0,<5.0.0)
Requires-Dist: pyqt6 (>=6.4.2,<7.0.0)
Requires-Dist: pyqtgraph (>=0.13.2,<0.14.0)
Requires-Dist: toml (>=0.10.2,<0.11.0)
Project-URL: Documentation, https://fringes.readthedocs.io/en/latest/getting_started/usage.html#graphical-user-interface
Project-URL: Repository, https://github.com/comimag/fringes-gui
